cpalgo/__init__.py
cpalgo/algo.py
cpalgo/caesar_cipher.py
cpalgo/chinese_remainder.py
cpalgo/convex_hull.py
cpalgo/count_primes.py
cpalgo/edit_distance.py
cpalgo/euler_phi.py
cpalgo/first_missing_positive.py
cpalgo/is_palindrome.py
cpalgo/is_valid_parantheses.py
cpalgo/kth_largest_element.py
cpalgo/longest_common_prefix.py
cpalgo/longest_common_subsequence.py
cpalgo/longest_increasing_subsequence.py
cpalgo/longest_palindromic_substring.py
cpalgo/longest_substring_without_repeating.py
cpalgo/maximum_product_subarray.py
cpalgo/maximum_subarray.py
cpalgo/minimum_window_substring.py
cpalgo/nCr_mod.py
cpalgo/three_sum.py
cpalgo/two_sum.py
cpalgo/unique_paths.py
cpalgo/word_break.py
cpalgo-1.1.4.dist-info/LICENSE.txt
cpalgo-1.1.4.dist-info/METADATA
cpalgo-1.1.4.dist-info/WHEEL
cpalgo-1.1.4.dist-info/top_level.txt
cpalgo-1.1.4.dist-info/RECORD
